README.md
setup.py
bcodparser/__init__.py
bcodparser.egg-info/PKG-INFO
bcodparser.egg-info/SOURCES.txt
bcodparser.egg-info/dependency_links.txt
bcodparser.egg-info/top_level.txt