Metadata-Version: 2.4
Name: bcodparser
Version: 1.0.1
Summary: Allows you to decode the Bluetooth Class of Device (CoD) field and interpret major, minor, and service classes.
Home-page: https://github.com/Lou-du-Poitou/bcodparser/
Author: V / Lou du Poitou
Author-email: v.loudupoitou@gmail.com
Maintainer: V / Lou du Poitou
Maintainer-email: v.loudupoitou@gmail.com
License: MIT
Dynamic: author
Dynamic: author-email
Dynamic: description
Dynamic: description-content-type
Dynamic: home-page
Dynamic: license
Dynamic: maintainer
Dynamic: maintainer-email
Dynamic: summary
